px4tuning/__init__.py
px4tuning/exemplo_vrft.py
px4tuning/exemplo_vrft2.py
px4tuning/importa.py
px4tuning/px4att.py
px4tuning/sysid.py
px4tuning/vrft.py
px4tuning-0.1.dist-info/LICENSE
px4tuning-0.1.dist-info/METADATA
px4tuning-0.1.dist-info/WHEEL
px4tuning-0.1.dist-info/entry_points.txt
px4tuning-0.1.dist-info/top_level.txt
px4tuning-0.1.dist-info/RECORD
