Metadata-Version: 2.1
Name: px4tuning
Version: 0.1
Summary: Auto tuning for PX4
Home-page: https://github.com/diegoeck/px4tuning
Author: Diego Eckhard
Author-email: diego@eckhard.com.br
License: MIT
Platform: UNKNOWN
Classifier: Programming Language :: Python :: 3
Classifier: License :: OSI Approved :: MIT License
Classifier: Operating System :: OS Independent
